MLDockKit/7te7_H_no_HOHandI0V.pdb
MLDockKit/7te7_original.pdb
MLDockKit/7te7_prepared.pdbqt
MLDockKit/MLDockKit.py
MLDockKit/__init__.py
MLDockKit/padel_model.joblib
mldockkit-0.1.2.dist-info/LICENSE
mldockkit-0.1.2.dist-info/METADATA
mldockkit-0.1.2.dist-info/WHEEL
mldockkit-0.1.2.dist-info/top_level.txt
mldockkit-0.1.2.dist-info/RECORD
