Metadata-Version: 2.2
Name: MLDockKit
Version: 0.1.2
Summary: Python package that calculates Lipinski descriptors, predicts pIC50, and performs docking
Home-page: https://github.com/clabe-wekesa/MLDockKit
Author: Edwin Mwakio, Clabe Wekesa, Patrick Okoth
Author-email: simiyu86wekesa@gmail.com
License: MIT
Classifier: Natural Language :: English
Classifier: Programming Language :: Python
Classifier: License :: OSI Approved :: MIT License
Classifier: Operating System :: OS Independent
Requires-Python: >=3.9
License-File: LICENSE
Requires-Dist: rdkit
Requires-Dist: pandas
Requires-Dist: padelpy
Requires-Dist: joblib
Requires-Dist: scikit-learn
Requires-Dist: scipy
Requires-Dist: gemmi
Requires-Dist: numpy
Dynamic: author
Dynamic: author-email
Dynamic: classifier
Dynamic: description
Dynamic: description-content-type
Dynamic: home-page
Dynamic: license
Dynamic: requires-dist
Dynamic: requires-python
Dynamic: summary
